[
  {
    "id": 1,
    "airline_code": "indigo",
    "airline": "Indigo",
    "number": "SJ-111",
    "from": "PUNE",
    "to": "DELHI",
    "from_code": "PNQ",
    "to_code": "DEL",
    "depart_date": "Sun Jul 22 2018 17:03:07 GMT+0530 (IST)",
    "arrive_date": "Sun Jul 22 2018 19:03:07 GMT+0530 (IST)",
    "price": 3000,
    "ticketavailable":4,
    "return_trip": {
      "airline": "indigo",
      "number": "SJ-211",
      "from": "DELHI",
      "to": "PUNE",
      "from_code": "DEL",
      "to_code": "PNQ",
      "depart_date": "Mon Jul 23 2018 10:03:07 GMT+0530 (IST)",
      "arrive_date": "Mon Jul 23 2018 12:03:07 GMT+0530 (IST)",
      "price": 3500,
      "ticketavailable":3
    }
  },
  {
    "id": 2,
    "airline_code": "indigo",
    "airline": "Indigo",
    "number": "SJ-112",
    "from": "DELHI",
    "to": "GOA",
    "from_code": "DEL",
    "to_code": "GOA",
    "depart_date": "Sun Jul 22 2018 20:03:07 GMT+0530 (IST)",
    "arrive_date": "Sun Jul 22 2018 22:03:07 GMT+0530 (IST)",
    "price": 3000,
    "ticketavailable":2,
    "return_trip": {
      "airline": "indigo",
      "number": "SJ-212",
      "from": "DELHI",
      "to": "GOA",
      "from_code": "DEL",
      "to_code": "GOA",
      "depart_date": "Mon Jul 23 2018 :03:07 GMT+0530 (IST)",
      "arrive_date": "Mon Jul 23 2018 12:03:07 GMT+0530 (IST)",
      "price": 3500,
      "ticketavailable":4
    }
  },
  {
    "id": 3,
    "airline_code": "spicejet",
    "airline": "Spicejet",
    "number": "SJ-113",
    "from": "PUNE",
    "to": "JAIPUR",
    "from_code": "PNQ",
    "to_code": "JAI",
    "depart_date": "Sun Jul 22 2018 17:03:07 GMT+0530 (IST)",
    "arrive_date": "Sun Jul 22 2018 19:03:07 GMT+0530 (IST)",
    "price": 3000,
    "ticketavailable":4,
    "return_trip": {
      "airline": "Spicejet",
      "number": "SJ-213",
      "from": "JAIPUR",
      "to": "PUNE",
      "from_code": "JAI",
      "to_code": "PNQ",
      "depart_date": "Mon Jul 23 2018 10:03:07 GMT+0530 (IST)",
      "arrive_date": "Mon Jul 23 2018 12:03:07 GMT+0530 (IST)",
      "price": 3500,
      "ticketavailable":3
    }
  },
  {
    "id": 1,
    "airline_code": "spicejet",
    "airline": "Spicejet",
    "number": "SJ-114",
    "from": "PUNE",
    "to": "DELHI",
    "from_code": "PNQ",
    "to_code": "DEL",
    "depart_date": "Tue Jul 24 2018 17:03:07 GMT+0530 (IST)",
    "arrive_date": "Tue Jul 24 2018 19:03:07 GMT+0530 (IST)",
    "price": 3000,
    "ticketavailable":9,
    "return_trip": {
      "airline": "Spicejet",
      "number": "SJ-214",
      "from": "DELHI",
      "to": "PUNE",
      "from_code": "DEL",
      "to_code": "PNQ",
      "depart_date": "Wed Jul 25 2018 10:03:07 GMT+0530 (IST)",
      "arrive_date": "Wed Jul 25 2018 12:03:07 GMT+0530 (IST)",
      "price": 3500,
      "ticketavailable":18
    }
  }
]